ship_it_validate/__init__.py
ship_it_validate-0.4.0.dist-info/METADATA
ship_it_validate-0.4.0.dist-info/WHEEL
ship_it_validate-0.4.0.dist-info/RECORD
