Metadata-Version: 2.1
Name: ship-it-validate
Version: 0.4.0
Summary: low-code authentication and billing
Home-page: https://ship-it.app
Author: Ship It
Author-email: info@ship-it.app
Requires-Python: >=3.8.1,<4.0.0
Classifier: Programming Language :: Python :: 3
Classifier: Programming Language :: Python :: 3.9
Classifier: Programming Language :: Python :: 3.10
Classifier: Programming Language :: Python :: 3.11
Requires-Dist: python-jose[cryptography] (>=3.3.0,<4.0.0)
Project-URL: Documentation, https://docs.ship-it.app
